rinoh_typeface_symbola/Symbola.ttf
rinoh_typeface_symbola/__init__.py
rinoh_typeface_symbola-0.1.1.dist-info/LICENSE
rinoh_typeface_symbola-0.1.1.dist-info/METADATA
rinoh_typeface_symbola-0.1.1.dist-info/WHEEL
rinoh_typeface_symbola-0.1.1.dist-info/entry_points.txt
rinoh_typeface_symbola-0.1.1.dist-info/top_level.txt
rinoh_typeface_symbola-0.1.1.dist-info/RECORD
