Metadata-Version: 2.1
Name: rinoh-typeface-symbola
Version: 0.1.1
Summary: Symbola typeface
Home-page: https://github.com/jemrobinson/rinoh-typeface-symbola
Author: James Robinson
Author-email: james.em.robinson+pypi@gmail.com
License: UNKNOWN
Project-URL: Bug Tracker, https://github.com/jemrobinson/rinoh-typeface-symbola/issues
Keywords: opentype,font
Platform: UNKNOWN
Classifier: Intended Audience :: Developers
Classifier: Intended Audience :: End Users/Desktop
Classifier: License :: OSI Approved :: MIT License
Classifier: Operating System :: OS Independent
Classifier: Programming Language :: Python
Classifier: Programming Language :: Python :: 3
Classifier: Topic :: Text Processing :: Fonts
Requires-Python: >=3.6
License-File: LICENSE
Requires-Dist: rinohtype
